[
  {
    "iduser" :  "001",
    "idperiod":"18001",
    "timesheet":{ "Data11": "1", "Data12": "2", "Data13": "3","Data14": "4","Data15": "5","Data16":"6","Data17":"7",
                  "Data21": "1", "Data22": "2", "Data23": "3","Data24": "4","Data25": "5","Data26":"6","Data27":"7",
                  "Data31": "1", "Data32": "2", "Data33": "3","Data34": "4","Data35": "5","Data36":"6","Data37":"7",
                  "Data41": "1", "Data42": "2", "Data43": "3","Data44": "4","Data45": "5","Data46":"6","Data47":"7"
                }

  },
  {
    "iduser": "002",
    "idperiod": "18002",
    "timesheet": { "Data11": "1", "Data12": "2", "Data13": "3","Data14": "4","Data15": "5","Data16":"6","Data17":"7",
                  "Data21": "1", "Data22": "2", "Data23": "3","Data24": "4","Data25": "5","Data26":"6","Data27":"7",
                  "Data31": "1", "Data32": "2", "Data33": "3","Data34": "4","Data35": "5","Data36":"6","Data37":"7",
                  "Data41": "1", "Data42": "2", "Data43": "3","Data44": "4","Data45": "5","Data46":"6","Data47":"7"
                }
  }
]
